pyqt_sql_demo/__init__.py
pyqt_sql_demo/app.py
pyqt_sql_demo/connection/__init__.py
pyqt_sql_demo/connection/error_handler.py
pyqt_sql_demo/connection/exceptions.py
pyqt_sql_demo/connection/model.py
pyqt_sql_demo/syntax_highlighter/sql.py
pyqt_sql_demo/widgets/__init__.py
pyqt_sql_demo/widgets/connection.py
pyqt_sql_demo/widgets/main.py
pyqt_sql_demo/widgets/text.py
pyqt_sql_demo-1.0.1.dist-info/entry_points.txt
pyqt_sql_demo-1.0.1.dist-info/WHEEL
pyqt_sql_demo-1.0.1.dist-info/METADATA
pyqt_sql_demo-1.0.1.dist-info/RECORD
