Metadata-Version: 2.1
Name: pyqt-sql-demo
Version: 1.0.1
Summary: PyQT SQL executor demo example using DB API (no QtSQL)
Home-page: https://github.com/vduseev/pyqt-sql-demo
License: MIT
Keywords: pyqt,sql,sqlite,qtableview
Author: vduseev
Author-email: vagiz@duseev.com
Requires-Python: >=3.8,<4.0
Classifier: License :: OSI Approved :: MIT License
Classifier: Programming Language :: Python :: 3
Classifier: Programming Language :: Python :: 3.8
Requires-Dist: pygments (>=2.6.1,<3.0.0)
Requires-Dist: pyqt5 (>=5.15.0,<6.0.0)
Project-URL: Documentation, https://github.com/vduseev/pyqt-sql-demo
Project-URL: Repository, https://github.com/vduseev/pyqt-sql-demo
